{
  "id": "thankful",
  "title": "Thankful",
  "artist": "Unknown",
  "audio": "audio/thankful.mp3",
  "duration": 120,
  "lines": [
    {
      "time": 0.0,
      "en": "I've got so much to be thankful for",
      "vi": "Tôi có quá nhiều điều để biết ơn"
    },
    {
      "time": 1.7,
      "en": "Look, I've got a roof and a bed",
      "vi": "Này, tôi có mái nhà và chiếc giường"
    },
    {
      "time": 6.7,
      "en": "A couple groceries to stay fed",
      "vi": "Vài thứ ăn uống để no qua ngày"
    },
    {
      "time": 9.9,
      "en": "I've got a phone and clean water",
      "vi": "Tôi có điện thoại và nước sạch"
    },
    {
      "time": 13.2,
      "en": "And some shoes when I wanna go farther",
      "vi": "Và đôi giày khi muốn bước đi xa hơn"
    },
    {
      "time": 16.9,
      "en": "Today I've got so much to be thankful for (hey)",
      "vi": "Hôm nay tôi có quá nhiều điều để biết ơn (hey)"
    },
    {
      "time": 22.4,
      "en": "I woke up this mornin' thinkin', \"Thank You, Lord\" (hey)",
      "vi": "Tôi thức dậy sáng nay nghĩ rằng, \"Cảm ơn Chúa\" (hey)"
    },
    {
      "time": 28.4,
      "en": "For giving me everything I could ever need and more",
      "vi": "Vì đã ban cho tôi mọi thứ tôi cần và hơn thế nữa"
    },
    {
      "time": 36.1,
      "en": "I've got so much to be thankful for (oh, yeah, run it back)",
      "vi": "Tôi có quá nhiều điều để biết ơn (oh, yeah, run it back)"
    },
    {
      "time": 41.7,
      "en": "Ay, I have lights and a fan",
      "vi": "Ay, tôi có đèn điện và quạt mát"
    },
    {
      "time": 46.3,
      "en": "A couple people who know who I am (know)",
      "vi": "Vài người biết tôi là ai (know)"
    },
    {
      "time": 51.1,
      "en": "I have a car (ay) and clean clothes",
      "vi": "Tôi có xe hơi (ay) và quần áo sạch"
    },
    {
      "time": 53.3,
      "en": "Pots and pans I can cook on a stove",
      "vi": "Nồi chảo để tôi nấu ăn trên bếp"
    },
    {
      "time": 57.5,
      "en": "I have the sun and air in my lungs",
      "vi": "Tôi có ánh nắng và không khí trong phổi"
    },
    {
      "time": 60.5,
      "en": "And a big mess that I get to clean up",
      "vi": "Và một mớ bừa bộn mà tôi được dọn dẹp"
    },
    {
      "time": 63.9,
      "en": "But most of all, one thing's true",
      "vi": "Nhưng trên tất cả, có một điều là thật"
    },
    {
      "time": 66.3,
      "en": "Jesus, I'm grateful for You (You, You, ah-hey)",
      "vi": "Lạy Chúa Giêsu, con biết ơn vì Ngài (Ngài, Ngài, ah-hey)"
    },
    {
      "time": 68.6,
      "en": "Today I've got so much to be thankful for (thankful for)",
      "vi": "Hôm nay tôi có quá nhiều điều để biết ơn (biết ơn)"
    },
    {
      "time": 75.7,
      "en": "I woke up this mornin' thinkin', \"Thank You, Lord\" (thank You)",
      "vi": "Tôi thức dậy sáng nay nghĩ rằng, \"Cảm ơn Chúa\" (cảm ơn)"
    },
    {
      "time": 81.7,
      "en": "For giving me (ay) everything (ay) I could ever need and more (need and more)",
      "vi": "Vì đã ban cho tôi (ay) mọi thứ (ay) tôi cần và hơn thế nữa (cần và hơn)"
    },
    {
      "time": 87.0,
      "en": "I've got so much to be thankful for (ay), mm, one more time",
      "vi": "Tôi có quá nhiều điều để biết ơn (ay), mm, thêm một lần nữa"
    },
    {
      "time": 87.5,
      "en": "Today I've got so much to be thankful for (thankful for)",
      "vi": "Hôm nay tôi có quá nhiều điều để biết ơn (biết ơn)"
    },
    {
      "time": 102.5,
      "en": "I woke up this mornin' thinkin', \"Thank You, Lord\" (thank You, Lord)",
      "vi": "Tôi thức dậy sáng nay nghĩ rằng, \"Cảm ơn Chúa\" (cảm ơn Chúa)"
    },
    {
      "time": 108.3,
      "en": "For giving me everything I could ever need and more",
      "vi": "Vì đã ban cho tôi mọi thứ tôi cần và hơn thế nữa"
    },
    {
      "time": 116.1,
      "en": "I've got so much to be thankful for (oh, say it again, say it again)",
      "vi": "Tôi có quá nhiều điều để biết ơn (oh, say it again, say it again)"
    },
    {
      "time": 116.4,
      "en": "I've got so much to be thankful for",
      "vi": "Tôi có quá nhiều điều để biết ơn"
    }
  ]
}